Metadata-Version: 2.1
Name: odoo11-addon-purchase-stock-picking-return-invoicing-force-invoiced
Version: 11.0.1.0.0.99.dev5
Summary: Glue module between purchase_force_invoiced and purchase_stock_picking_return_invoicing
Home-page: https://github.com/OCA/account-invoicing
Author: Eficent,Odoo Community Association (OCA)
Author-email: support@odoo-community.org
License: AGPL-3
Platform: UNKNOWN
Classifier: Programming Language :: Python
Classifier: Framework :: Odoo
Classifier: Framework :: Odoo :: 11.0
Classifier: License :: OSI Approved :: GNU Affero General Public License v3
Classifier: Development Status :: 4 - Beta
Requires-Python: >=2.7, !=3.0.*, !=3.1.*, !=3.2.*, !=3.3.*, !=3.4.*
Requires-Dist: odoo11-addon-purchase-force-invoiced
Requires-Dist: odoo11-addon-purchase-stock-picking-return-invoicing
Requires-Dist: odoo <11.1dev,>=11.0a
